jabs_mimir/DataBlockWrapper.py
jabs_mimir/Mimir.py
jabs_mimir/MimirPaginator.py
jabs_mimir/MimirUtils.py
jabs_mimir/UtilityModule.py
jabs_mimir/__init__.py
jabs_mimir/mimirThemeManager.py
jabs_mimir-0.8.26.dist-info/licenses/license
jabs_mimir-0.8.26.dist-info/METADATA
jabs_mimir-0.8.26.dist-info/WHEEL
jabs_mimir-0.8.26.dist-info/top_level.txt
jabs_mimir-0.8.26.dist-info/RECORD
