Metadata-Version: 2.4
Name: jabs-mimir
Version: 0.8.26
Summary: A reusable tkinter/ttkbootstrap UI framework
Author-email: William Lydahl <william.lydahl@jabs.se>
License-Expression: MIT
Classifier: Programming Language :: Python :: 3.11
Classifier: Operating System :: OS Independent
Requires-Python: >=3.11
License-File: license
Dynamic: license-file
